{"v":"5.7.13","fr":60,"ip":0,"op":121,"w":512,"h":512,"nm":"question","ddd":0,"assets":[],"layers":[{"ddd":0,"ind":1,"ty":4,"nm":"Layer 3 Outlines","sr":1,"ks":{"o":{"a":0,"k":100,"ix":11},"r":{"a":1,"k":[{"i":{"x":[0],"y":[1]},"o":{"x":[0.333],"y":[0]},"t":10,"s":[0]},{"t":30,"s":[360]}],"ix":10},"p":{"a":1,"k":[{"i":{"x":0,"y":1},"o":{"x":0.333,"y":0},"t":10,"s":[256,208.453,0],"to":[0,-13.833,0],"ti":[0,-2.5,0]},{"i":{"x":0.667,"y":1},"o":{"x":1,"y":0},"t":20,"s":[256,125.453,0],"to":[0,2.5,0],"ti":[0,-12,0]},{"i":{"x":0.667,"y":1},"o":{"x":0.333,"y":0},"t":30,"s":[256,223.453,0],"to":[0,12,0],"ti":[0,2.5,0]},{"i":{"x":0.667,"y":1},"o":{"x":0.333,"y":0},"t":40,"s":[256,197.453,0],"to":[0,-2.5,0],"ti":[0,-1.833,0]},{"t":48,"s":[256,208.453,0]}],"ix":2,"l":2},"a":{"a":0,"k":[153.731,172.892,0],"ix":1,"l":2},"s":{"a":0,"k":[100,100,100],"ix":6,"l":2}},"ao":0,"shapes":[{"ty":"gr","it":[{"ind":0,"ty":"sh","ix":1,"ks":{"a":0,"k":{"i":[[0,0],[-18.958,0],[0,-29.063],[29.063,0],[0,0]],"o":[[9.263,-15.038],[29.063,0],[0,29.063],[0,0],[0,0]],"v":[[-48.731,-42.828],[-3.893,-67.892],[48.731,-15.268],[-3.893,37.355],[-3.893,67.892]],"c":false},"ix":2},"nm":"Path 1","mn":"ADBE Vector Shape - Group","hd":false},{"ty":"st","c":{"a":0,"k":[0,0,0,1],"ix":3},"o":{"a":0,"k":100,"ix":4},"w":{"a":0,"k":42,"ix":5},"lc":2,"lj":2,"bm":0,"nm":"Stroke 1","mn":"ADBE Vector Graphic - Stroke","hd":false},{"ty":"tr","p":{"a":0,"k":[153.731,172.892],"ix":2},"a":{"a":0,"k":[0,0],"ix":1},"s":{"a":0,"k":[100,100],"ix":3},"r":{"a":0,"k":0,"ix":6},"o":{"a":0,"k":100,"ix":7},"sk":{"a":0,"k":0,"ix":4},"sa":{"a":0,"k":0,"ix":5},"nm":"Transform"}],"nm":"Group 1","np":2,"cix":2,"bm":0,"ix":1,"mn":"ADBE Vector Group","hd":false}],"ip":0,"op":360,"st":0,"bm":0},{"ddd":0,"ind":2,"ty":4,"nm":"Layer 2 Outlines","sr":1,"ks":{"o":{"a":0,"k":100,"ix":11},"r":{"a":0,"k":0,"ix":10},"p":{"a":1,"k":[{"i":{"x":0,"y":1},"o":{"x":0.333,"y":0},"t":0,"s":[255.975,349.598,0],"to":[0,-8.333,0],"ti":[0,-3.167,0]},{"i":{"x":0.667,"y":1},"o":{"x":1,"y":0},"t":10,"s":[255.975,299.598,0],"to":[0,3.167,0],"ti":[0,-6.667,0]},{"i":{"x":0.667,"y":1},"o":{"x":0.333,"y":0},"t":20,"s":[255.975,368.598,0],"to":[0,6.667,0],"ti":[0,3.167,0]},{"i":{"x":0.667,"y":1},"o":{"x":0.333,"y":0},"t":30,"s":[255.975,339.598,0],"to":[0,-3.167,0],"ti":[0,-1.667,0]},{"t":38,"s":[255.975,349.598,0]}],"ix":2,"l":2},"a":{"a":0,"k":[23.255,22.091,0],"ix":1,"l":2},"s":{"a":0,"k":[100,100,100],"ix":6,"l":2}},"ao":0,"shapes":[{"ty":"gr","it":[{"ind":0,"ty":"sh","ix":1,"ks":{"a":0,"k":{"i":[[8.342,-7.772],[-8.167,-8.234],[-5.567,-0.025],[-4.01,3.865],[8.108,8.286]],"o":[[-8.235,8.167],[3.92,3.953],[5.569,-0.046],[8.108,-8.286],[-8.34,-7.773]],"v":[[-14.716,-14.069],[-14.838,15.629],[-0.022,21.841],[14.897,15.751],[14.897,-14.067]],"c":true},"ix":2},"nm":"Path 1","mn":"ADBE Vector Shape - Group","hd":false},{"ty":"fl","c":{"a":0,"k":[0,0,0,1],"ix":4},"o":{"a":0,"k":100,"ix":5},"r":1,"bm":0,"nm":"Fill 1","mn":"ADBE Vector Graphic - Fill","hd":false},{"ty":"tr","p":{"a":0,"k":[23.255,22.091],"ix":2},"a":{"a":0,"k":[0,0],"ix":1},"s":{"a":0,"k":[100,100],"ix":3},"r":{"a":0,"k":0,"ix":6},"o":{"a":0,"k":100,"ix":7},"sk":{"a":0,"k":0,"ix":4},"sa":{"a":0,"k":0,"ix":5},"nm":"Transform"}],"nm":"Group 1","np":2,"cix":2,"bm":0,"ix":1,"mn":"ADBE Vector Group","hd":false}],"ip":0,"op":360,"st":0,"bm":0}],"markers":[]}